useful_rdkit_utils/__init__.py
useful_rdkit_utils/build_ring_dictionary.py
useful_rdkit_utils/descriptors.py
useful_rdkit_utils/geometry.py
useful_rdkit_utils/jupyter_utils.py
useful_rdkit_utils/misc_utils.py
useful_rdkit_utils/optional.py
useful_rdkit_utils/pandas_utils.py
useful_rdkit_utils/reactions.py
useful_rdkit_utils/reos.py
useful_rdkit_utils/ring_systems.py
useful_rdkit_utils/scaffold_finder.py
useful_rdkit_utils/seaborn_utils.py
useful_rdkit_utils/silly_walks.py
useful_rdkit_utils/split_utils.py
useful_rdkit_utils/stat_utils.py
useful_rdkit_utils/units.py
useful_rdkit_utils/data/ring_systems/chembl_ring_systems.parquet
useful_rdkit_utils-0.96.dist-info/METADATA
useful_rdkit_utils-0.96.dist-info/WHEEL
useful_rdkit_utils-0.96.dist-info/licenses/LICENSE
useful_rdkit_utils-0.96.dist-info/RECORD
