Metadata-Version: 2.4
Name: useful_rdkit_utils
Version: 0.96
Summary: A collection of useful RDKit functions
Project-URL: Homepage, https://github.com/PatWalters/useful_rdkit_utils
Project-URL: Bug Tracker, https://github.com/PatWalters/useful_rdkit_utils/issues
Author-email: Pat Walters <wpwalters@gmail.com>
License-File: LICENSE
Classifier: License :: OSI Approved :: MIT License
Classifier: Operating System :: OS Independent
Classifier: Programming Language :: Python :: 3
Requires-Python: >=3.11
Requires-Dist: dataclasses
Requires-Dist: numpy
Requires-Dist: pandas
Requires-Dist: py3dmol
Requires-Dist: pyarrow
Requires-Dist: pystow
Requires-Dist: rdkit
Requires-Dist: scikit-learn
Requires-Dist: scipy
Requires-Dist: seaborn
Requires-Dist: tqdm
Provides-Extra: extras
Requires-Dist: click; extra == 'extras'
Requires-Dist: umap-learn; extra == 'extras'
Provides-Extra: tests
Requires-Dist: pytest; extra == 'tests'
